fengwo/__init__.py
fengwo/pyML.pyd
fengwo/libcrypto-3-x64.dll
fengwo-0.0.7.dist-info/METADATA
fengwo-0.0.7.dist-info/WHEEL
fengwo-0.0.7.dist-info/top_level.txt
fengwo-0.0.7.dist-info/RECORD
